LICENSE.txt
README.md
setup.cfg
setup.py
sampa/__init__.py
sampa/__main__.py
sampa.egg-info/PKG-INFO
sampa.egg-info/SOURCES.txt
sampa.egg-info/dependency_links.txt
sampa.egg-info/entry_points.txt
sampa.egg-info/requires.txt
sampa.egg-info/top_level.txt
sampa/src/HeteroStructure_Generator.py
sampa/src/SAMBA_HeteroStructure.input
sampa/src/SAMBA_WorkFlow.input
sampa/src/_info_pseudo.py
sampa/src/bader
sampa/src/bader_poscar.py
sampa/src/bader_update.py
sampa/src/charge_transfer.py
sampa/src/chgsum.pl
sampa/src/contcar_update.py
sampa/src/energy_scan.py
sampa/src/job.py
sampa/src/kpoints.py
sampa/src/make_files.py
sampa/src/output.py
sampa/src/potcar.py
sampa/src/xy-scan.py
sampa/src/xy-scan_analysis.py
sampa/src/z-scan.py
sampa/src/z-scan_analysis.py
sampa/src/INPUTS/INCAR_bader
sampa/src/INPUTS/INCAR_bader.SO
sampa/src/INPUTS/INCAR_bands
sampa/src/INPUTS/INCAR_bands.SO
sampa/src/INPUTS/INCAR_dos
sampa/src/INPUTS/INCAR_dos.SO
sampa/src/INPUTS/INCAR_relax
sampa/src/INPUTS/INCAR_scf
sampa/src/INPUTS/INCAR_scf.SO
sampa/src/INPUTS/INCAR_xy-scan
sampa/src/INPUTS/INCAR_z-scan
sampa/src/INPUTS/inputs_VASProcar/input.vasprocar.bands
sampa/src/INPUTS/inputs_VASProcar/input.vasprocar.chgcar
sampa/src/INPUTS/inputs_VASProcar/input.vasprocar.dos
sampa/src/INPUTS/inputs_VASProcar/input.vasprocar.location
sampa/src/INPUTS/inputs_VASProcar/input.vasprocar.locpot
sampa/src/INPUTS/inputs_VASProcar/input.vasprocar.orbitals
sampa/src/INPUTS/inputs_VASProcar/input.vasprocar.spin