Metadata-Version: 2.1
Name: sampa
Version: 1.0.0.43
Summary: ...
Author: Augusto de Lelis Araujo
Author-email: augusto-lelis@outlook.com
License: Closed source
License-File: LICENSE.txt
